simpy_events/__init__.py
simpy_events/event.py
simpy_events/manager.py
simpy_events-0.0.1.dist-info/METADATA
simpy_events-0.0.1.dist-info/RECORD
simpy_events-0.0.1.dist-info/WHEEL
simpy_events-0.0.1.dist-info/top_level.txt
tests/__init__.py
tests/test_cases.py
tests/test_event.py
tests/test_manager.py
tests/test_pep8.py
