Metadata-Version: 2.1
Name: simpy-events
Version: 0.0.1
Summary: event system with simpy to decouple simulation code and increase reusability
Home-page: https://github.com/loicpw/simpy-events
Author: Loïc Peron
Author-email: peronloic.us@gmail.com
License: MIT License
Download-URL: https://github.com/loicpw/simpy-events.git
Platform: UNKNOWN
Classifier: Development Status :: 3 - Alpha
Classifier: Intended Audience :: Developers
Classifier: License :: OSI Approved :: MIT License
Classifier: Natural Language :: English
Classifier: Programming Language :: Python
Classifier: Programming Language :: Python :: 3.6
Classifier: Programming Language :: Python :: 3.7
